dejawidth/__init__.py
dejawidth/default-widths.json
dejawidth/measure.py
dejawidth-0.1.1.dist-info/METADATA
dejawidth-0.1.1.dist-info/WHEEL
dejawidth-0.1.1.dist-info/top_level.txt
dejawidth-0.1.1.dist-info/RECORD
