Metadata-Version: 2.1
Name: dejawidth
Version: 0.1.1
Summary: measure the width, in pixels, of a string rendered using dejavu sans 110pt
Author: Rahul Jha
Author-email: rj722@protonmail.com
Requires-Python: >=3.7,<4.0
